{
  "POLYMARKET_KALSHI_MAPPING": {
    "Moneyline_Events": {
      "sports": [
        {
          "polymarket_ticker": "aec-ipl-pbks-raj-2026-04-28",
          "kalshi_ticker": "KXIPLGAME-26APR28RRPBKS-PBKS",
          "other_poly_id": "aec-ipl-pbks-raj-2026-04-28-inverse",
          "other_kalshi_ticker": "KXIPLGAME-26APR28RRPBKS-RR"
        },
        {
          "polymarket_ticker": "aec-ipl-dcap-rcb-2026-04-27",
          "kalshi_ticker": "KXIPLGAME-26APR27RCBDC-DC",
          "other_poly_id": "aec-ipl-dcap-rcb-2026-04-27-inverse",
          "other_kalshi_ticker": "KXIPLGAME-26APR27RCBDC-RCB"
        },
        {
          "polymarket_ticker": "aec-ipl-lsg-kkr-2026-04-26",
          "kalshi_ticker": "KXIPLGAME-26APR26KKRLSG-LSG",
          "other_poly_id": "aec-ipl-lsg-kkr-2026-04-26-inverse",
          "other_kalshi_ticker": "KXIPLGAME-26APR26KKRLSG-KKR"
        },
        {
          "polymarket_ticker": "aec-ipl-csk-guj-2026-04-26",
          "kalshi_ticker": "KXIPLGAME-26APR26CSKGT-CSK",
          "other_poly_id": "aec-ipl-csk-guj-2026-04-26-inverse",
          "other_kalshi_ticker": "KXIPLGAME-26APR26CSKGT-GT"
        },
        {
          "polymarket_ticker": "aec-ufc-germee-jacmal-2026-05-02",
          "kalshi_ticker": "KXUFCFIGHT-26MAY02MALMEE-MEE",
          "other_poly_id": "aec-ufc-germee-jacmal-2026-05-02-inverse",
          "other_kalshi_ticker": "KXUFCFIGHT-26MAY02MALMEE-MAL"
        },
        {
          "polymarket_ticker": "aec-lol-ns-t1-2026-04-29",
          "kalshi_ticker": "KXLOLGAME-26APR290400T1NS-NS",
          "other_poly_id": "aec-lol-ns-t1-2026-04-29-inverse",
          "other_kalshi_ticker": "KXLOLGAME-26APR290400T1NS-T1"
        },
        {
          "polymarket_ticker": "aec-mlb-mia-lad-2026-04-27",
          "kalshi_ticker": "KXMLBGAME-26APR272210MIALAD-MIA",
          "other_poly_id": "aec-mlb-mia-lad-2026-04-27-inverse",
          "other_kalshi_ticker": "KXMLBGAME-26APR272210MIALAD-LAD"
        },
        {
          "polymarket_ticker": "aec-mlb-chc-sd-2026-04-27",
          "kalshi_ticker": "KXMLBGAME-26APR272140CHCSD-CHC",
          "other_poly_id": "aec-mlb-chc-sd-2026-04-27-inverse",
          "other_kalshi_ticker": "KXMLBGAME-26APR272140CHCSD-SD"
        },
        {
          "polymarket_ticker": "aec-mlb-nyy-tex-2026-04-27",
          "kalshi_ticker": "KXMLBGAME-26APR272005NYYTEX-NYY",
          "other_poly_id": "aec-mlb-nyy-tex-2026-04-27-inverse",
          "other_kalshi_ticker": "KXMLBGAME-26APR272005NYYTEX-TEX"
        },
        {
          "polymarket_ticker": "aec-mlb-sea-min-2026-04-27",
          "kalshi_ticker": "KXMLBGAME-26APR271940SEAMIN-SEA",
          "other_poly_id": "aec-mlb-sea-min-2026-04-27-inverse",
          "other_kalshi_ticker": "KXMLBGAME-26APR271940SEAMIN-MIN"
        },
        {
          "polymarket_ticker": "aec-mlb-laa-cws-2026-04-27",
          "kalshi_ticker": "KXMLBGAME-26APR271940LAACWS-LAA",
          "other_poly_id": "aec-mlb-laa-cws-2026-04-27-inverse",
          "other_kalshi_ticker": "KXMLBGAME-26APR271940LAACWS-CWS"
        },
        {
          "polymarket_ticker": "aec-mlb-bos-tor-2026-04-27",
          "kalshi_ticker": "KXMLBGAME-26APR271907BOSTOR-BOS",
          "other_poly_id": "aec-mlb-bos-tor-2026-04-27-inverse",
          "other_kalshi_ticker": "KXMLBGAME-26APR271907BOSTOR-TOR"
        },
        {
          "polymarket_ticker": "aec-mlb-stl-pit-2026-04-27",
          "kalshi_ticker": "KXMLBGAME-26APR271840STLPIT-STL",
          "other_poly_id": "aec-mlb-stl-pit-2026-04-27-inverse",
          "other_kalshi_ticker": "KXMLBGAME-26APR271840STLPIT-PIT"
        },
        {
          "polymarket_ticker": "aec-mlb-tb-cle-2026-04-27",
          "kalshi_ticker": "KXMLBGAME-26APR271810TBCLE-TB",
          "other_poly_id": "aec-mlb-tb-cle-2026-04-27-inverse",
          "other_kalshi_ticker": "KXMLBGAME-26APR271810TBCLE-CLE"
        },
        {
          "polymarket_ticker": "aec-mlb-laa-kc-2026-04-26",
          "kalshi_ticker": "KXMLBGAME-26APR261920LAAKC-LAA",
          "other_poly_id": "aec-mlb-laa-kc-2026-04-26-inverse",
          "other_kalshi_ticker": "KXMLBGAME-26APR261920LAAKC-KC"
        },
        {
          "polymarket_ticker": "aec-mlb-chc-lad-2026-04-26",
          "kalshi_ticker": "KXMLBGAME-26APR261610CHCLAD-CHC",
          "other_poly_id": "aec-mlb-chc-lad-2026-04-26-inverse",
          "other_kalshi_ticker": "KXMLBGAME-26APR261610CHCLAD-LAD"
        },
        {
          "polymarket_ticker": "aec-mlb-sd-az-2026-04-26",
          "kalshi_ticker": "KXMLBGAME-26APR261605SDAZ-SD",
          "other_poly_id": "aec-mlb-sd-az-2026-04-26-inverse",
          "other_kalshi_ticker": "KXMLBGAME-26APR261605SDAZ-AZ"
        },
        {
          "polymarket_ticker": "aec-mlb-mia-sf-2026-04-26",
          "kalshi_ticker": "KXMLBGAME-26APR261605MIASF-MIA",
          "other_poly_id": "aec-mlb-mia-sf-2026-04-26-inverse",
          "other_kalshi_ticker": "KXMLBGAME-26APR261605MIASF-SF"
        },
        {
          "polymarket_ticker": "aec-mlb-sea-stl-2026-04-26",
          "kalshi_ticker": "KXMLBGAME-26APR261415SEASTL-SEA",
          "other_poly_id": "aec-mlb-sea-stl-2026-04-26-inverse",
          "other_kalshi_ticker": "KXMLBGAME-26APR261415SEASTL-STL"
        },
        {
          "polymarket_ticker": "aec-mlb-wsh-cws-2026-04-26",
          "kalshi_ticker": "KXMLBGAME-26APR261410WSHCWS-WSH",
          "other_poly_id": "aec-mlb-wsh-cws-2026-04-26-inverse",
          "other_kalshi_ticker": "KXMLBGAME-26APR261410WSHCWS-CWS"
        },
        {
          "polymarket_ticker": "aec-mlb-pit-mil-2026-04-26",
          "kalshi_ticker": "KXMLBGAME-26APR261410PITMIL-PIT",
          "other_poly_id": "aec-mlb-pit-mil-2026-04-26-inverse",
          "other_kalshi_ticker": "KXMLBGAME-26APR261410PITMIL-MIL"
        },
        {
          "polymarket_ticker": "aec-mlb-nyy-hou-2026-04-26",
          "kalshi_ticker": "KXMLBGAME-26APR261410NYYHOU-NYY",
          "other_poly_id": "aec-mlb-nyy-hou-2026-04-26-inverse",
          "other_kalshi_ticker": "KXMLBGAME-26APR261410NYYHOU-HOU"
        },
        {
          "polymarket_ticker": "aec-mlb-min-tb-2026-04-26",
          "kalshi_ticker": "KXMLBGAME-26APR261340MINTB-MIN",
          "other_poly_id": "aec-mlb-min-tb-2026-04-26-inverse",
          "other_kalshi_ticker": "KXMLBGAME-26APR261340MINTB-TB"
        },
        {
          "polymarket_ticker": "aec-mlb-det-cin-2026-04-26",
          "kalshi_ticker": "KXMLBGAME-26APR261340DETCIN-DET",
          "other_poly_id": "aec-mlb-det-cin-2026-04-26-inverse",
          "other_kalshi_ticker": "KXMLBGAME-26APR261340DETCIN-CIN"
        },
        {
          "polymarket_ticker": "aec-mlb-col-nym-2026-04-26",
          "kalshi_ticker": "KXMLBGAME-26APR261340COLNYM-COL",
          "other_poly_id": "aec-mlb-col-nym-2026-04-26-inverse",
          "other_kalshi_ticker": "KXMLBGAME-26APR261340COLNYM-NYM"
        },
        {
          "polymarket_ticker": "aec-mlb-cle-tor-2026-04-26",
          "kalshi_ticker": "KXMLBGAME-26APR261337CLETOR-CLE",
          "other_poly_id": "aec-mlb-cle-tor-2026-04-26-inverse",
          "other_kalshi_ticker": "KXMLBGAME-26APR261337CLETOR-TOR"
        },
        {
          "polymarket_ticker": "aec-mlb-phi-atl-2026-04-26",
          "kalshi_ticker": "KXMLBGAME-26APR261335PHIATL-PHI",
          "other_poly_id": "aec-mlb-phi-atl-2026-04-26-inverse",
          "other_kalshi_ticker": "KXMLBGAME-26APR261335PHIATL-ATL"
        },
        {
          "polymarket_ticker": "aec-mlb-bos-bal-2026-04-26",
          "kalshi_ticker": "KXMLBGAME-26APR261335BOSBAL-BOS",
          "other_poly_id": "aec-mlb-bos-bal-2026-04-26-inverse",
          "other_kalshi_ticker": "KXMLBGAME-26APR261335BOSBAL-BAL"
        },
        {
          "polymarket_ticker": "aec-mlb-col-nym-2026-04-25",
          "kalshi_ticker": "KXMLBGAME-26APR251610COLNYM-COL",
          "other_poly_id": "aec-mlb-col-nym-2026-04-25-inverse",
          "other_kalshi_ticker": "KXMLBGAME-26APR251610COLNYM-NYM"
        },
        {
          "polymarket_ticker": "aec-nba-por-sa-2026-04-28",
          "kalshi_ticker": "KXNBAGAME-26APR28PORSAS-POR",
          "other_poly_id": "aec-nba-por-sa-2026-04-28-inverse",
          "other_kalshi_ticker": "KXNBAGAME-26APR28PORSAS-SAS"
        },
        {
          "polymarket_ticker": "aec-nba-min-den-2026-04-27",
          "kalshi_ticker": "KXNBAGAME-26APR27MINDEN-MIN",
          "other_poly_id": "aec-nba-min-den-2026-04-27-inverse",
          "other_kalshi_ticker": "KXNBAGAME-26APR27MINDEN-DEN"
        },
        {
          "polymarket_ticker": "aec-nba-okc-pho-2026-04-27",
          "kalshi_ticker": "KXNBAGAME-26APR27OKCPHX-OKC",
          "other_poly_id": "aec-nba-okc-pho-2026-04-27-inverse",
          "other_kalshi_ticker": "KXNBAGAME-26APR27OKCPHX-PHX"
        },
        {
          "polymarket_ticker": "aec-nba-det-orl-2026-04-27",
          "kalshi_ticker": "KXNBAGAME-26APR27DETORL-DET",
          "other_poly_id": "aec-nba-det-orl-2026-04-27-inverse",
          "other_kalshi_ticker": "KXNBAGAME-26APR27DETORL-ORL"
        },
        {
          "polymarket_ticker": "aec-nba-sa-por-2026-04-26",
          "kalshi_ticker": "KXNBAGAME-26APR26SASPOR-SAS",
          "other_poly_id": "aec-nba-sa-por-2026-04-26-inverse",
          "other_kalshi_ticker": "KXNBAGAME-26APR26SASPOR-POR"
        },
        {
          "polymarket_ticker": "aec-nba-cle-tor-2026-04-26",
          "kalshi_ticker": "KXNBAGAME-26APR26CLETOR-CLE",
          "other_poly_id": "aec-nba-cle-tor-2026-04-26-inverse",
          "other_kalshi_ticker": "KXNBAGAME-26APR26CLETOR-TOR"
        },
        {
          "polymarket_ticker": "aec-wta-arysab-naoosa-2026-04-27",
          "kalshi_ticker": "KXWTAMATCH-26APR27SABOSA-SAB",
          "other_poly_id": "aec-wta-arysab-naoosa-2026-04-27-inverse",
          "other_kalshi_ticker": "KXWTAMATCH-26APR27SABOSA-OSA"
        },
        {
          "polymarket_ticker": "aec-wta-anapot-jelost-2026-04-25",
          "kalshi_ticker": "KXWTAMATCH-26APR25POTOST-POT",
          "other_poly_id": "aec-wta-anapot-jelost-2026-04-25-inverse",
          "other_kalshi_ticker": "KXWTAMATCH-26APR25POTOST-OST"
        },
        {
          "polymarket_ticker": "aec-wta-elimer-karpli-2026-04-25",
          "kalshi_ticker": "KXWTAMATCH-26APR25MERPLI-MER",
          "other_poly_id": "aec-wta-elimer-karpli-2026-04-25-inverse",
          "other_kalshi_ticker": "KXWTAMATCH-26APR25MERPLI-PLI"
        },
        {
          "polymarket_ticker": "aec-atp-stetsi-danagu-2026-04-27",
          "kalshi_ticker": "KXATPMATCH-26APR27TSIMER-TSI",
          "other_poly_id": "aec-atp-stetsi-danagu-2026-04-27-inverse",
          "other_kalshi_ticker": "KXATPMATCH-26APR27TSIMER-MER"
        },
        {
          "polymarket_ticker": "aec-atp-camnor-thitir-2026-04-26",
          "kalshi_ticker": "KXATPMATCH-26APR26NORTIR-NOR",
          "other_poly_id": "aec-atp-camnor-thitir-2026-04-26-inverse",
          "other_kalshi_ticker": "KXATPMATCH-26APR26NORTIR-TIR"
        },
        {
          "polymarket_ticker": "aec-atp-karkha-jakmen-2026-04-26",
          "kalshi_ticker": "KXATPMATCH-26APR26KHAMEN-KHA",
          "other_poly_id": "aec-atp-karkha-jakmen-2026-04-26-inverse",
          "other_kalshi_ticker": "KXATPMATCH-26APR26KHAMEN-MEN"
        },
        {
          "polymarket_ticker": "aec-atp-talgri-lormus-2026-04-26",
          "kalshi_ticker": "KXATPMATCH-26APR26GRIMUS-GRI",
          "other_poly_id": "aec-atp-talgri-lormus-2026-04-26-inverse",
          "other_kalshi_ticker": "KXATPMATCH-26APR26GRIMUS-MUS"
        },
        {
          "polymarket_ticker": "aec-atp-alefok-casruu-2026-04-26",
          "kalshi_ticker": "KXATPMATCH-26APR26DAVRUU-DAV",
          "other_poly_id": "aec-atp-alefok-casruu-2026-04-26-inverse",
          "other_kalshi_ticker": "KXATPMATCH-26APR26DAVRUU-RUU"
        },
        {
          "polymarket_ticker": "aec-atp-fracer-lucdar-2026-04-26",
          "kalshi_ticker": "KXATPMATCH-26APR26CERDAR-CER",
          "other_poly_id": "aec-atp-fracer-lucdar-2026-04-26-inverse",
          "other_kalshi_ticker": "KXATPMATCH-26APR26CERDAR-DAR"
        },
        {
          "polymarket_ticker": "aec-atp-jacken-nisbas-2026-04-26",
          "kalshi_ticker": "KXATPCHALLENGERMATCH-26APR26KENBAS-KEN",
          "other_poly_id": "aec-atp-jacken-nisbas-2026-04-26-inverse",
          "other_kalshi_ticker": "KXATPCHALLENGERMATCH-26APR26KENBAS-BAS"
        },
        {
          "polymarket_ticker": "aec-ufc-timell-steerc-2026-05-02",
          "kalshi_ticker": "KXUFCFIGHT-26MAY02ELLERC-ELL",
          "other_poly_id": "aec-ufc-timell-steerc-2026-05-02-inverse",
          "other_kalshi_ticker": "KXUFCFIGHT-26MAY02ELLERC-ERC"
        },
        {
          "polymarket_ticker": "aec-lol-ns-t1-2026-04-29",
          "kalshi_ticker": "KXLOLMAP-26APR290400T1NS-2-NS",
          "other_poly_id": "aec-lol-ns-t1-2026-04-29-inverse",
          "other_kalshi_ticker": "KXLOLMAP-26APR290400T1NS-2-T1"
        },
        {
          "polymarket_ticker": "aec-lol-ns-t1-2026-04-29",
          "kalshi_ticker": "KXLOLMAP-26APR290400T1NS-1-NS",
          "other_poly_id": "aec-lol-ns-t1-2026-04-29-inverse",
          "other_kalshi_ticker": "KXLOLMAP-26APR290400T1NS-1-T1"
        },
        {
          "polymarket_ticker": "aec-lol-kt-hle-2026-04-29",
          "kalshi_ticker": "KXLOLGAME-26APR290600HLEKT-KT",
          "other_poly_id": "aec-lol-kt-hle-2026-04-29-inverse",
          "other_kalshi_ticker": "KXLOLGAME-26APR290600HLEKT-HLE"
        },
        {
          "polymarket_ticker": "aec-lol-nip-jdg-2026-04-29",
          "kalshi_ticker": "KXLOLGAME-26APR290500JDGNIP-NIP",
          "other_poly_id": "aec-lol-nip-jdg-2026-04-29-inverse",
          "other_kalshi_ticker": "KXLOLGAME-26APR290500JDGNIP-JDG"
        },
        {
          "polymarket_ticker": "aec-lol-ig-al-2026-04-28",
          "kalshi_ticker": "KXLOLGAME-26APR280500ALIG-IG",
          "other_poly_id": "aec-lol-ig-al-2026-04-28-inverse",
          "other_kalshi_ticker": "KXLOLGAME-26APR280500ALIG-AL"
        },
        {
          "polymarket_ticker": "aec-mlb-ath-tex-2026-04-26",
          "kalshi_ticker": "KXMLBGAME-26APR261435ATHTEX-ATH",
          "other_poly_id": "aec-mlb-ath-tex-2026-04-26-inverse",
          "other_kalshi_ticker": "KXMLBGAME-26APR261435ATHTEX-TEX"
        },
        {
          "polymarket_ticker": "aec-nba-cle-tor-2026-04-26",
          "kalshi_ticker": "KXMLBGAME-26APR261337CLETOR-CLE",
          "other_poly_id": "aec-nba-cle-tor-2026-04-26-inverse",
          "other_kalshi_ticker": "KXMLBGAME-26APR261337CLETOR-TOR"
        },
        {
          "polymarket_ticker": "aec-nba-lal-hou-2026-04-26",
          "kalshi_ticker": "KXNBAGAME-26APR26LALHOU-LAL",
          "other_poly_id": "aec-nba-lal-hou-2026-04-26-inverse",
          "other_kalshi_ticker": "KXNBAGAME-26APR26LALHOU-HOU"
        },
        {
          "polymarket_ticker": "aec-atp-dalsvr-andgue-2026-04-26",
          "kalshi_ticker": "KXATPCHALLENGERMATCH-26APR26SVRGUE-SVR",
          "other_poly_id": "aec-atp-dalsvr-andgue-2026-04-26-inverse",
          "other_kalshi_ticker": "KXATPCHALLENGERMATCH-26APR26SVRGUE-GUE"
        },
        {
          "polymarket_ticker": "aec-nba-lal-hou-2026-04-26",
          "kalshi_ticker": "KXNBASERIES-26HOULALR1-LAL",
          "other_poly_id": "aec-nba-lal-hou-2026-04-26-inverse",
          "other_kalshi_ticker": "KXNBASERIES-26HOULALR1-HOU"
        },
        {
          "polymarket_ticker": "aec-ufc-bendar-quisal-2026-05-02",
          "kalshi_ticker": "KXUFCFIGHT-26MAY02DARSAL-DAR",
          "other_poly_id": "aec-ufc-bendar-quisal-2026-05-02-inverse",
          "other_kalshi_ticker": "KXUFCFIGHT-26MAY02DARSAL-SAL"
        },
        {
          "polymarket_ticker": "aec-ufc-shagaz-braper-2026-05-02",
          "kalshi_ticker": "KXUFCFIGHT-26MAY02GAZPER-GAZ",
          "other_poly_id": "aec-ufc-shagaz-braper-2026-05-02-inverse",
          "other_kalshi_ticker": "KXUFCFIGHT-26MAY02GAZPER-PER"
        },
        {
          "polymarket_ticker": "aec-nba-atl-ny-2026-04-28",
          "kalshi_ticker": "KXNBAGAME-26APR28ATLNYK-ATL",
          "other_poly_id": "aec-nba-atl-ny-2026-04-28-inverse",
          "other_kalshi_ticker": "KXNBAGAME-26APR28ATLNYK-NYK"
        },
        {
          "polymarket_ticker": "aec-nba-phi-bos-2026-04-28",
          "kalshi_ticker": "KXNBAGAME-26APR28PHIBOS-PHI",
          "other_poly_id": "aec-nba-phi-bos-2026-04-28-inverse",
          "other_kalshi_ticker": "KXNBAGAME-26APR28PHIBOS-BOS"
        },
        {
          "polymarket_ticker": "aec-nba-bos-phi-2026-04-26",
          "kalshi_ticker": "KXNBAGAME-26APR26BOSPHI-BOS",
          "other_poly_id": "aec-nba-bos-phi-2026-04-26-inverse",
          "other_kalshi_ticker": "KXNBAGAME-26APR26BOSPHI-PHI"
        },
        {
          "polymarket_ticker": "aec-mlb-cle-tor-2026-04-26",
          "kalshi_ticker": "KXNBAGAME-26APR26CLETOR-CLE",
          "other_poly_id": "aec-mlb-cle-tor-2026-04-26-inverse",
          "other_kalshi_ticker": "KXNBAGAME-26APR26CLETOR-TOR"
        },
        {
          "polymarket_ticker": "aec-atp-stetsi-danagu-2026-04-27",
          "kalshi_ticker": "KXATPSETWINNER-26APR27TSIMER-2-TSI",
          "other_poly_id": "aec-atp-stetsi-danagu-2026-04-27-inverse",
          "other_kalshi_ticker": "KXATPSETWINNER-26APR27TSIMER-2-MER"
        },
        {
          "polymarket_ticker": "aec-atp-stetsi-danagu-2026-04-27",
          "kalshi_ticker": "KXATPSETWINNER-26APR27TSIMER-1-TSI",
          "other_poly_id": "aec-atp-stetsi-danagu-2026-04-27-inverse",
          "other_kalshi_ticker": "KXATPSETWINNER-26APR27TSIMER-1-MER"
        },
        {
          "polymarket_ticker": "aec-atp-camnor-thitir-2026-04-26",
          "kalshi_ticker": "KXATPSETWINNER-26APR26NORTIR-1-NOR",
          "other_poly_id": "aec-atp-camnor-thitir-2026-04-26-inverse",
          "other_kalshi_ticker": "KXATPSETWINNER-26APR26NORTIR-1-TIR"
        },
        {
          "polymarket_ticker": "aec-atp-karkha-jakmen-2026-04-26",
          "kalshi_ticker": "KXATPSETWINNER-26APR26KHAMEN-2-KHA",
          "other_poly_id": "aec-atp-karkha-jakmen-2026-04-26-inverse",
          "other_kalshi_ticker": "KXATPSETWINNER-26APR26KHAMEN-2-MEN"
        },
        {
          "polymarket_ticker": "aec-atp-karkha-jakmen-2026-04-26",
          "kalshi_ticker": "KXATPSETWINNER-26APR26KHAMEN-1-KHA",
          "other_poly_id": "aec-atp-karkha-jakmen-2026-04-26-inverse",
          "other_kalshi_ticker": "KXATPSETWINNER-26APR26KHAMEN-1-MEN"
        },
        {
          "polymarket_ticker": "aec-atp-fracer-lucdar-2026-04-26",
          "kalshi_ticker": "KXATPSETWINNER-26APR26CERDAR-1-CER",
          "other_poly_id": "aec-atp-fracer-lucdar-2026-04-26-inverse",
          "other_kalshi_ticker": "KXATPSETWINNER-26APR26CERDAR-1-DAR"
        }
      ]
    }
  }
}